dsaria/__init__.py
dsaria/heap.py
dsaria/linked_list.py
dsaria/sort.py
dsaria-1.5.0.dist-info/licenses/LICENSE
tests/data_structures/test_heap.py
tests/data_structures/test_linked_list.py
tests/sorting/test_bogosort.py
tests/sorting/test_bubble_sort.py
tests/sorting/test_counting_sort.py
dsaria-1.5.0.dist-info/METADATA
dsaria-1.5.0.dist-info/WHEEL
dsaria-1.5.0.dist-info/top_level.txt
dsaria-1.5.0.dist-info/RECORD
