Metadata-Version: 2.4
Name: dsaria
Version: 1.5.0
Summary: A simple Python library for data structures and algorithms.
Author-email: Rahil Shaik <rahil15973@gmail.com>
License: MIT License
Project-URL: Homepage, https://github.com/rahils1/dsaria
Project-URL: BugTracker, https://github.com/rahilshaik/dsaria/issues
Requires-Python: >=3.9
License-File: LICENSE
Dynamic: license-file
